ParkerO/__init__.py
ParkerO/interfacetovgg.py
ParkerO/plt_tools.py
ParkerO/vggtointerface.py
ParkerO-0.0.1.dist-info/LICENSE
ParkerO-0.0.1.dist-info/METADATA
ParkerO-0.0.1.dist-info/WHEEL
ParkerO-0.0.1.dist-info/top_level.txt
ParkerO-0.0.1.dist-info/RECORD
