Metadata-Version: 2.1
Name: ParkerO
Version: 0.0.1
Summary: ParkerO is a Python-based implementation of the Parker-Oldenburg Algorithm for calculating gravity anomalies from a density interface and Recovering the density interface from gravity anomalies.
Author: Eurrreak
Author-email: z1714833751@163.com
Requires-Python: >=3.6
License-File: LICENSE
